ratelimit/__init__.py
ratelimit/__main__.py
ratelimit/config.example.py
ratelimit/config.py
ratelimit/key.py
ratelimit/limit.py
ratelimit/log.py
ratelimit/organization.py
ratelimit/organization_project.py
ratelimit/project.py
ratelimit/project_key.py
ratelimit/request.py
ratelimit/cli/__init__.py
ratelimit/cli/imports.py
ratelimit/cli/commands/__init__.py
ratelimit/cli/commands/add.py
ratelimit/cli/commands/cleanup.py
ratelimit/cli/commands/delete.py
ratelimit/cli/commands/describe.py
ratelimit/cli/commands/get.py
ratelimit/cli/commands/help.py
ratelimit/cli/commands/init.py
ratelimit/cli/commands/set.py
ratelimit/cli/commands/sync.py
ratelimit/cli/commands/update.py
ratelimit/db/__init__.py
ratelimit/db/base.py
ratelimit/db/key.py
ratelimit/db/limit.py
ratelimit/db/migrate.py
ratelimit/db/model.py
ratelimit/db/organization.py
ratelimit/db/organization_project.py
ratelimit/db/project.py
ratelimit/db/project_key.py
ratelimit/sentry/__init__.py
ratelimit/sentry/key.py
ratelimit/sentry/organization.py
ratelimit/sentry/project.py
ratelimit/utils/__init__.py
ratelimit/utils/json.py
ratelimit/utils/types.py
sentry_rate_limit-0.0.2.dist-info/METADATA
sentry_rate_limit-0.0.2.dist-info/WHEEL
sentry_rate_limit-0.0.2.dist-info/entry_points.txt
sentry_rate_limit-0.0.2.dist-info/top_level.txt
sentry_rate_limit-0.0.2.dist-info/RECORD
