Metadata-Version: 2.1
Name: sentry-rate-limit
Version: 0.0.2
Summary: Rate limiter for the sentry.
Home-page: https://github.com/antohhh93/sentry-rate-limit
Author: Anton Turko
Author-email: anton_turko@mail.ru
License: UNKNOWN
Platform: UNKNOWN
Classifier: Intended Audience :: Developers
Classifier: Intended Audience :: System Administrators
Classifier: Operating System :: POSIX :: Linux
Classifier: Programming Language :: Python :: 3
Classifier: Programming Language :: Python :: 3.9
Classifier: Topic :: Software Development
Requires-Dist: click (==8.1.3)
Requires-Dist: requests (==2.28.1)
Requires-Dist: peewee (==3.15.4)
Requires-Dist: psycopg2-binary (==2.9.5)
Requires-Dist: prettytable (==3.6.0)
